octopolars-1.1.7.dist-info/METADATA
octopolars-1.1.7.dist-info/WHEEL
octopolars-1.1.7.dist-info/entry_points.txt
octopolars-1.1.7.dist-info/licenses/LICENSE
octopols/__init__.py
octopols/auth.py
octopols/cli.py
octopols/exprs.py
octopols/inventory.py
octopols/issues.py
octopolars-1.1.7.dist-info/RECORD
