Metadata-Version: 2.1
Name: octopolars
Version: 1.1.7
Summary: Pull, filter, walk, and read a GitHub user's repositories with Polars.
Keywords: fsspec,github,polars,repositories
Author-Email: Louis Maddox <louismmx@gmail.com>
License: MIT
Classifier: Development Status :: 4 - Beta
Classifier: Intended Audience :: Developers
Classifier: License :: OSI Approved :: MIT License
Classifier: Natural Language :: English
Classifier: Operating System :: OS Independent
Classifier: Programming Language :: Python :: 3
Classifier: Programming Language :: Python :: 3.10
Classifier: Programming Language :: Python :: 3.11
Classifier: Programming Language :: Python :: 3.12
Classifier: Programming Language :: Python :: 3.13
Classifier: Programming Language :: Python :: 3.9
Classifier: Programming Language :: Python :: Implementation :: CPython
Classifier: Programming Language :: Python
Project-URL: Documentation, https://octopolars.vercel.app/
Project-URL: Homepage, https://github.com/lmmx/octopols
Project-URL: Repository, https://github.com/lmmx/octopols.git
Requires-Python: >=3.11
Requires-Dist: click>=8.1.8
Requires-Dist: dulwich>=0.22.7
Requires-Dist: fsspec[github]>=2025.2.0
Requires-Dist: platformdirs>=4.3.6
Requires-Dist: polars-expr-hopper>=1.1.0
Requires-Dist: pygithub>=2.8.0
Requires-Dist: requests>=2.32.3
Requires-Dist: universal-pathlib>=0.2.6
Provides-Extra: polars
Requires-Dist: polars>=1.21.0; extra == "polars"
Provides-Extra: polars-lts-cpu
Requires-Dist: polars-lts-cpu>=1.21.0; extra == "polars-lts-cpu"
